sentry_hal
