Metadata-Version: 1.1
Name: sentry-hal
Version: 0.1.2
Summary: A Sentry extension which integrates with a JSON based XMPP chat bot
Home-page: http://www.github.com/alexnvdias
Author: Alexandre Dias
Author-email: alexnvdias@gmail.com
License: BSD
Platform: UNKNOWN
Classifier: Framework :: Django
Classifier: Intended Audience :: Developers
Classifier: Intended Audience :: System Administrators
Classifier: Operating System :: OS Independent
Classifier: Topic :: Software Development
